fma_connect/__init__.py
fma_connect/clients.py
fma_connect/exceptions.py
fma_connect/settings.py
fma_connect/version.py
fma_connect-0.0.2.dist-info/METADATA
fma_connect-0.0.2.dist-info/WHEEL
fma_connect-0.0.2.dist-info/top_level.txt
fma_connect-0.0.2.dist-info/RECORD
